{"run_number": "1667437095336912", "step_name": "start", "task_id": "1", "attempt_id": 0, "name": "_graph_info", "content_type": "gzip+pickle-v2", "type": "metaflow.artifact", "sha": "3091f3befdea1e4b56f5b790fb5a6d0856c5cb68", "ds_type": "local", "location": ":root:/Users/qinyixin/Desktop/7773_assignement/.metaflow", "flow_id": "BayesridgeFlow", "user_name": "qinyixin", "tags": [], "system_tags": ["metaflow_version:2.5.0", "user:qinyixin", "runtime:dev", "date:2022-11-03", "python_version:3.9.12"], "ts_epoch": 1667437095811}